{
  "id": "piano_card",
  "title": "Аккорды и гаммы для фортепиано (пианино) - обучающие карточки A4, таблица аккордов, теория музыки",
  "description_short": "Обучающие карточки A4: аккорды и гаммы для фортепиано, таблица аккордов, теория музыки.",
  "description_full": "Аккорды и гаммы для фортепиано (пианино) — обучающие карточки A4. Таблица аккордов, теория музыки.",
  "image_main": "images/products/piano_card/main.jpg",
  "image_thumb": "images/products/piano_card/thumb.jpg",
  "category": "Музыка",
  "has_digital": false,
  "digital_price": null,
  "digital_format": null,
  "link_ozon": "https://www.ozon.ru/product/akkordy-i-gammy-dlya-fortepiano-pianino-obuchayushchie-kartochki-a4-tablitsa-akkordov-teoriya-muzyki-3009258309/",
  "link_wb": "https://www.wildberries.ru/catalog/480941779/detail.aspx?targetUrl=GP"
}
